{"00":"DİZÜSTÜ","44":"GERİLLA","01":"KURUMLAŞMA","45":"DELİCİLİK","02":"DUYULMAMIŞ","46":"YIPRATMAK","03":"EŞRAFLIK","47":"KAVAKÇI","04":"FIRINLAMAK","48":"PANTEİZM","05":"ISPANAKLAR","49":"DÖVÜŞME","06":"ÇENTİKLİ","07":"TAKUNYACI","08":"KANALIYLA","09":"ERGUVAN","50":"MUHARRİK","51":"TRAPEZLİ","52":"DURDURULMAK","53":"GÜVERCİNLER","10":"ALDEHİT","54":"KOMPLEKSLİ","11":"DEPLASMAN","55":"ŞİNANAY","12":"YAŞLILIK","56":"EDİLGEN","13":"SÜRESİZLİK","57":"DEKORATİF","14":"SUSATMAK","58":"HAFIZALI","15":"İRKİLME","59":"MEKANİZE","16":"REDDETMEK","17":"TAHAYYÜL","18":"TOSLAŞMA","19":"KAYNAŞMA","20":"ŞİŞİRTME","21":"SAPARTA","22":"MİMLEMEK","23":"ÇALIŞKAN","24":"DİNAMİTLEMEK","25":"GAZİLİK","26":"KURUMLU","27":"CEVAPLAMA","28":"SÜTÇÜLÜK","29":"OVALAMAK","30":"ETİKETÇİ","31":"SERTİFİKASIZ","32":"GENİŞLETME","33":"MİNİBÜSÇÜ","34":"DOKUNMA","35":"MUTEBER","36":"TEPKİME","37":"POHPOHLAMAK","38":"GRAVÜRCÜ","39":"TIKLAYABİLME","40":"YERİLME","41":"EDEBİNİ","42":"KOMİSYONCU","43":"ERİŞMEK"}