{"00":"MUTLUCA","44":"HALKACI","01":"KULÜPLER","45":"İCATÇILIK","02":"TUTKALLI","46":"İTİLMEK","03":"DÜŞÜNCESİNİ","47":"DÜŞÜNDÜRTMEK","04":"İMANSIZ","48":"MEDENİYET","05":"KALECİLİK","49":"BLOKLAŞMA","06":"KIRKBUDAK","07":"OLAĞANLAŞMAK","08":"KÖŞESİNE","09":"TANIKLI","50":"MİNYATÜR","51":"PEKMEZLİK","52":"SÜSSÜZLÜK","53":"KÜRESEL","10":"KAFATASÇI","54":"GÖZÜKME","11":"ÖZGÜRCE","55":"KALABALIKLIK","12":"TAKUNYASIZ","56":"HARAÇÇI","13":"DAYANILMAK","57":"TATİLCİLİK","14":"GÖZENEKLİ","58":"DETAYSIZ","15":"MEMLEKETLER","59":"NOKTALANMAK","16":"ŞALVARLI","17":"SADAKATSİZ","18":"DARGINLIK","19":"ÇÖMELME","20":"İHTİYATLILIK","21":"PARABELLUM","22":"TEHLİKESİZ","23":"BİRDENBİRE","24":"SİROZLU","25":"ÖKSÜRÜP","26":"HİDROKSİL","27":"TAZARRU","28":"İŞKEMBESİ","29":"ISMARLAMAK","30":"NİHAYET","31":"HACİMSİZLİK","32":"KARALEYLEK","33":"BAŞGARDİYAN","34":"KARAKABARCIK","35":"RADYASYONLU","36":"FIRINLANMA","37":"KONUŞKANLIK","38":"TAKADDÜM","39":"BULANMAK","40":"KARMAŞIKLIK","41":"DEVALÜE","42":"YÖNETMELİK","43":"SECDEYE"}