{"00":"FALAKAYA","44":"BURKULMA","01":"KÜFLENME","45":"PARTİLİ","02":"TUTULMUŞ","46":"ÇINARLIK","03":"TANIDIK","47":"ŞİTAİYE","04":"SENTAKTİK","48":"YORGUNLUĞUNU","05":"DELİŞMEN","49":"TUZAKLAMAK","06":"PAZARCI","07":"MEVDUAT","08":"ADAMCIK","09":"KUTUPSAL","50":"SANATSAL","51":"MUHTEMEL","52":"KLAVSENCİ","53":"PERİŞAN","10":"MERKEZCE","54":"TAÇLANDIRMA","11":"BİLHASSA","55":"İHTİYAÇSIZ","12":"KOLASIZ","56":"UYARLANMAK","13":"İLAÇSIZ","57":"SABAHLEYİN","14":"SAVSAMA","58":"EBLEHLİK","15":"DİNDARLIK","59":"PLEBİSİT","16":"ÖNERİDE","17":"REKREASYON","18":"ÇİFTEHANE","19":"KELEPÇELEMEK","20":"SİYAHIMSI","21":"FEVKANİ","22":"URGANCILIK","23":"YÜKSELTMEK","24":"SİNDİRİLMEK","25":"DAVRANIŞSAL","26":"ANLATIM","27":"KİLOAMPER","28":"ZİYAFET","29":"YILDIRIMLARI","30":"PLANKTON","31":"OTOMOTİV","32":"KOLTUKÇU","33":"KOMPRİME","34":"KOZMOLOJİK","35":"AKILLIM","36":"SOLUKLUK","37":"ŞAİBESİZ","38":"ÇAKIŞMALI","39":"MEVSİMLİK","40":"DİKTATÖRCE","41":"SİMGELEME","42":"KERPETEN","43":"ŞEMSİYE"}