{"00":"KİNDARLIK","44":"ABDESTLİ","01":"BARBUTÇU","45":"DALAMAN","02":"ŞIPPADAK","46":"SARSINTI","03":"KALORİMETRE","47":"ALATURKALIK","04":"İMTİZAÇLI","48":"MÜTTEFİKLİK","05":"BEZGİNLİK","49":"ZIRLAMA","06":"APANSIZIN","07":"GERGİNCE","08":"YARIŞTIRMAK","09":"ÇOBANLIK","50":"PLONJON","51":"DARALMA","52":"VABESTE","53":"GARDINI","10":"KESİNLİK","54":"MODİFİKASYON","11":"DÖVMESİZ","55":"ÖLÇÜSÜZCE","12":"ABDESTİNDE","56":"ELİMİNASYON","13":"PÜSKÜRÜK","57":"ADLANDIRILMA","14":"ŞEKERCİLİK","58":"BADANASIZ","15":"ŞARTLILIK","59":"BOHÇASINI","16":"KİMYONLU","17":"DUYULUR","18":"BULANIŞ","19":"APAYDIN","20":"PARTİZAN","21":"AKINCILAR","22":"KAÇABİLME","23":"HEMCİNS","24":"GILLIGIŞSIZ","25":"KONABİLMEK","26":"YAŞANABİLME","27":"ESPRİLİ","28":"MALİKİLİK","29":"TAPINMAK","30":"ELLİNCİ","31":"İLERLEYİŞ","32":"KARALANMA","33":"MASARİF","34":"KUZGUNİ","35":"KEMİKLERİ","36":"KUSURLULUK","37":"AYLIKSIZ","38":"SALAHİYETLİ","39":"ETÇİLLER","40":"ANAHTARI","41":"MÜHÜRLENME","42":"ZERZEVAT","43":"REHBERLİK"}