{"00":"KENARDA","44":"BAHANELİ","01":"YERLİLİK","45":"GUARANİ","02":"REFORMCULUK","46":"ÇÖKKÜNLEŞME","03":"KERHANE","47":"LEVAZIM","04":"MAKASTAR","48":"AVUTMAK","05":"PEYLEME","49":"LEKELEMEK","06":"GETİRTMEK","07":"GECELEMEK","08":"YEDİKLERİ","09":"ALELITLAK","50":"TOPUKLAMAK","51":"ZANNEDİLMEK","52":"MUVASALAT","53":"MİKROPLU","10":"YAMAMAK","54":"ÇEMBERSEL","11":"BATIRMA","55":"HASTALANMAK","12":"İLTİHAPLI","56":"MÜZİKÇİ","13":"MANCINIK","57":"PARABOL","14":"GİZLİCE","58":"ISITABİLMEK","15":"OKUYUCU","59":"ÇEKİLMEK","16":"PETUNYA","17":"UZANIVERMEK","18":"IŞINLANMAK","19":"KAZMACI","20":"DELİKSİZ","21":"KARAMANLICA","22":"GEÇİRİVERMEK","23":"PSİKİYATRİST","24":"BUGÜNKÜ","25":"İSTİFADE","26":"ÇIPLAKLIK","27":"BOŞBOĞAZLIK","28":"İZZETİNEFİS","29":"KUYRUĞU","30":"LEKESİZ","31":"SUSAMAK","32":"HESAPLICA","33":"YAŞANMA","34":"HAPİSHANE","35":"EZBERLENMEK","36":"ALİTERASYON","37":"MELANET","38":"YÖNELTİLMEK","39":"GERÇEKLEŞME","40":"FOYASINI","41":"ARSLANLI","42":"GÖTÜRME","43":"ÇELEBİLEŞME"}