{"00":"REFERANDUM","44":"İŞTİYAK","01":"YUTTURMAK","45":"ELEMELİ","02":"TESVİYECİLİK","46":"PATENTİNİN","03":"HASETLİK","47":"KONSÜLTASYON","04":"KEPAZELİK","48":"KOKUSUNU","05":"KARAÇAYIR","49":"TERSLENMEK","06":"TAŞLAMACILIK","07":"EBEDİYET","08":"BEYİNSİZCE","09":"PATIRTILI","50":"YÜREĞİNİN","51":"KAKAVAN","52":"BOZUŞTURMAK","53":"ÇİZMEYİ","10":"MÜTEESSİF","54":"HIRSSIZ","11":"ONAYLATILMAK","55":"BİLİNÇALTI","12":"KAYBOLMAK","56":"SELAMLAYIŞ","13":"GELECEKÇİ","57":"ÇELİKLİ","14":"GEÇMİŞLİ","58":"KAZAKLIK","15":"DİRENÇSİZ","59":"ÇANTACILIK","16":"YAPTIRABİLME","17":"BİTEVİYE","18":"DAMITIM","19":"ALEYHTE","20":"KAZANILMAK","21":"TERLEME","22":"MÜSEMMEN","23":"ETKİLEYİCİ","24":"PAZARLANMA","25":"TAKILMAK","26":"YÜKSELEBİLME","27":"KUKLALIK","28":"YÜKSELTİ","29":"BEYZBOL","30":"AFFEDEBİLME","31":"SIZLAMAK","32":"FIRFIRLI","33":"KİTABET","34":"ŞINGIRDAMA","35":"KİLİTSİZ","36":"FISILDAŞMA","37":"PARANIN","38":"BINGILDAK","39":"ARİFLİK","40":"MUHTELİF","41":"KONSANTRE","42":"PİŞİRME","43":"DEMLENDİRMEK"}