{"00":"DARALTMAK","44":"TEZKERECİLİK","01":"HAFİFLEME","45":"RESİMSİ","02":"TANITLAMA","46":"KELİMESİ","03":"DENETLEMEK","47":"GÖBEKLİCE","04":"PİŞMANİYECİ","48":"DUYMAZLIKTAN","05":"BİTLENMEK","49":"YERLİLEŞME","06":"KALIPLAMAK","07":"YAVAŞLIK","08":"SECİYELİ","09":"KİŞİLİKLİ","50":"ZİYANSIZ","51":"KORUYUCULUK","52":"MÜTESELSİL","53":"GÜNEYDOĞU","10":"KAMAŞTIRMAK","54":"ODYOVİZÜEL","11":"GESTAPO","55":"TÜKETEBİLMEK","12":"GÜLDÜRÜ","56":"MİNARECİK","13":"LEGALLİK","57":"PALMİYE","14":"MELODİSİZ","58":"YERLERİ","15":"TÜLBENT","59":"MÜFSİTLİK","16":"KODAMAN","17":"ALIŞKANLIK","18":"KUŞATILMAK","19":"ISFAHAN","20":"DÖKÜNTÜLÜK","21":"GİZLETMEK","22":"RADYASYON","23":"İÇTİMAİYAT","24":"ZEHİRLENME","25":"BELİRGİN","26":"HOLDİNG","27":"LİSTELEMEK","28":"CUMHURİYETÇİ","29":"BERBERLİK","30":"MÜFETTİŞLİK","31":"ZÜHREVİ","32":"DEVRALMAK","33":"TAVIRLI","34":"ÇATIŞTIRMAK","35":"ARAŞTIRTMAK","36":"YAKALANIŞ","37":"SUİKAST","38":"PARTİSYON","39":"MÜFTÜLÜK","40":"TEPİŞMEK","41":"SAPTAMA","42":"CIRMALAMAK","43":"PANTOLONLU"}