{"00":"ÇÖZÜLÜŞ","44":"HACCETMEK","01":"TIRPANDAN","45":"GÖMLEKLİK","02":"DİYALİZE","46":"BLOKSUZ","03":"BOYUNDURUK","47":"EKMEDİĞİ","04":"ALKOLİKLİK","48":"HASTALANMAK","05":"TOMBULCA","49":"YİYİCİLİK","06":"EROTİZM","07":"HAVUZLAMAK","08":"ÖLDÜRÜLMEK","09":"KAŞARLANMAK","50":"MUZMAHİL","51":"KAPISIZLIK","52":"MÜZİKSEL","53":"DÜNÜRCÜLÜK","10":"HİZİPLEŞME","54":"İŞLERLİK","11":"ATAERKİ","55":"BORÇLANMAK","12":"KÖFTELİK","56":"BEĞENDİRMEK","13":"MÜNTEHA","57":"KULÜPÇÜ","14":"KOLONYA","58":"MÜHÜRLENME","15":"GÖNENÇLİ","59":"PESTENKERANİ","16":"GÜVENSİZ","17":"BENZİNLİ","18":"SİYASALLIK","19":"YAMPİRİ","20":"MÜSTAKİLEN","21":"ÇİRKİNCE","22":"AZİZLİK","23":"KUYRUKLULAR","24":"SANTRHAF","25":"SAYGILICA","26":"SAÇMACI","27":"HIZLICA","28":"TAHTAKURUSU","29":"BİYOPSİ","30":"SOLCULUK","31":"PEKİŞTİRME","32":"BÜYÜKTEN","33":"BUYURUN","34":"YENİLMEK","35":"ENDODERM","36":"MEHABET","37":"PUSUCULUK","38":"BEŞLEMEK","39":"DENGELEME","40":"ÇİFTLEŞTİRME","41":"SULTANOĞLU","42":"AYRANCILIK","43":"OKUNABİLME"}