{"00":"VERDİRMEK","44":"BERBERLİK","01":"DÜPEDÜZ","45":"KURDELE","02":"FIRSATTAN","46":"VASIFLI","03":"TELGRAF","47":"SATTIRMA","04":"ATAVİZM","48":"ÖLÇÜMLEME","05":"MUVAZZAF","49":"İLAHİYAT","06":"AYRIKSI","07":"TADINDAN","08":"PALAVRACI","09":"KUŞBAŞI","50":"ZIRTAPOZCA","51":"GÖRÜNDÜ","52":"KARINLAMA","53":"YETERLİ","10":"MEYDANA","54":"ALICILIK","11":"SOĞUTUCU","55":"GERİCİLİK","12":"MEZARINI","56":"UYGARCA","13":"TASDİKNAME","57":"HALLOLMAK","14":"ERGENLEŞME","58":"SEĞİRTMEK","15":"SÜREDURUM","59":"DİLEYEBİLMEK","16":"LEVENTLİK","17":"HAYIRDIR","18":"KROMOZOM","19":"OTURTMAK","20":"KAMIŞSI","21":"KEDİNİN","22":"GÖRÜŞÜLMEK","23":"AYRIŞABİLMEK","24":"ENGELLENME","25":"AŞILAYABİLME","26":"VERİLMEK","27":"GÖRENEKÇİ","28":"KAVURMACI","29":"MİNERAL","30":"MAHVOLMA","31":"TOPUKLU","32":"MAZERETSİZ","33":"NUMARACILIK","34":"SABUNSUZ","35":"KİREÇLİ","36":"OLUVERMEK","37":"BURKMAK","38":"DAĞARCIK","39":"BABADAN","40":"AKSIRMA","41":"SEFERLİK","42":"HÜRMETSİZLİK","43":"GÖNDERMEK"}