{"00":"HAKEMLİ","44":"EMREDEBİLME","01":"YELLENMEK","45":"KONUŞMACI","02":"BAZİLİKA","46":"SPEKTROSKOPİ","03":"KANALİZASYON","47":"ŞAŞIRIP","04":"İKİRCİKLİK","48":"GARDIFREN","05":"YOZLAŞTIRMAK","49":"İTİŞMEK","06":"İÇTENLİKSİZ","07":"SAPKINLIK","08":"ÇİRKİNLEŞME","09":"ENSTRÜMANTAL","50":"DUYUMSAMAK","51":"ALAVERE","52":"YENİLERDE","53":"MÜRİTLİK","10":"KÜÇÜKBAŞ","54":"BİNDİRMEK","11":"EKZOTERMİK","55":"BOTANİKÇİ","12":"ÇAĞLAYAN","56":"FEMİNİZM","13":"KAPTIRMA","57":"DAMAKSIZ","14":"AŞABİLMEK","58":"HAYALPEREST","15":"ATLATILIŞ","59":"İŞKİLLİ","16":"SANATÇILIK","17":"DAZLAKLAŞMA","18":"DENEKLİK","19":"İSTİFİNİ","20":"ABLATİF","21":"KIRATLIK","22":"KAPLANBOĞAN","23":"UĞRAYABİLME","24":"KURGULANMAK","25":"GÖNÜLSÜZCE","26":"BOYANMAK","27":"HAHAMBAŞILIK","28":"CEPÇİLİK","29":"KORSANLIK","30":"KIRKLANMA","31":"ŞEHİRLİLEŞME","32":"TOSLAMAK","33":"SÜLFÜRİK","34":"İDMANLI","35":"RAKİPSİZLİK","36":"ÇEKİLME","37":"EGZOZCU","38":"FÜSUNLU","39":"HURDASI","40":"YEMEKÇİLİK","41":"İLANİHAYE","42":"ŞUURSUZLUK","43":"ISSIZCA"}