{"00":"TARAYABİLME","44":"ENVAİÇEŞİT","01":"PUSUCULUK","45":"KOVBOYLUK","02":"PARLAMAK","46":"İKİRCİKLİLİK","03":"ALTYAPISAL","47":"PERDELEME","04":"MEMEDEN","48":"ÇIRÇIPLAK","05":"TANITILMA","49":"DEVRİDAİM","06":"DERİVASYON","07":"BİBEHRE","08":"ÇELİŞKİSİZ","09":"İLİŞKİLİ","50":"BÜYÜSÜZ","51":"ARKALANMAK","52":"PROLETER","53":"MARATONCULUK","10":"LAİSİZM","54":"TAKİPÇİ","11":"BENZETİLMEK","55":"ÜMMETÇİLİK","12":"LENFOMA","56":"KADINLAR","13":"BENZEYİŞ","57":"KABUKLAŞMA","14":"DİFRAKSİYON","58":"PERİTON","15":"ISINMAK","59":"KALIPLI","16":"ESNETEBİLME","17":"MECRASINDA","18":"OĞUZLAR","19":"MAHRUTİ","20":"ÇÖZÜNDÜRME","21":"TEHACÜM","22":"YAŞANMAK","23":"KADERCİLİK","24":"SOKAKTA","25":"ÇIKABİLMEK","26":"ETEĞİNİ","27":"MİLYARDER","28":"LOKMACI","29":"KAŞKORSE","30":"ESTETİK","31":"KAVRAMAK","32":"AYDINCA","33":"DANGADAK","34":"BEŞERİYET","35":"ELEŞTİRMECİ","36":"HAFTAYA","37":"FLAMANCA","38":"KANTOCU","39":"GICIRTILI","40":"HÖYKÜRMEK","41":"KARANTİNA","42":"DÜNYACI","43":"YELKESEN"}