{"00":"MÜSAVAT","44":"ÇEVİRTTİRMEK","01":"TROPİKA","45":"OLDUBİTTİYE","02":"KARYOLA","46":"MANDEPSİYE","03":"ADAMOTU","47":"GAYRİAHLAKİ","04":"BÜRYANCI","48":"DEĞİRMENE","05":"HARAMZADE","49":"KARTOGRAF","06":"KIRLANGIÇ","07":"KÜNYESİNİ","08":"KOLAYCILIK","09":"AKROBASİ","50":"PİRİNCİ","51":"YENİLENME","52":"GÜNGÖRMÜŞ","53":"BULAŞABİLMEK","10":"SALLANDIRMA","54":"PASAKLI","11":"OLUŞTURMAK","55":"ÇAĞRIŞIMSIZ","12":"ÇANTACI","56":"ELBİSELİK","13":"DURAKSIZ","57":"DIŞLAYIŞ","14":"KIVRILABİLME","58":"TOKALAŞMA","15":"KORKUSUZCA","59":"KOLAYLAŞMAK","16":"ÇİLEDEN","17":"DONANMASIZ","18":"KAPAKLI","19":"DEKOVİL","20":"OYUNBAZ","21":"ETİKETLENMEK","22":"BOKLAMA","23":"MAKASTAR","24":"TIRMALANMA","25":"SOKTURMAK","26":"BAŞTABİP","27":"SOKTURMA","28":"EKONOMETRİ","29":"KASIMPATI","30":"BİRLEŞMEK","31":"İKTİSATÇILIK","32":"BASTIRMAK","33":"ŞAŞILIK","34":"SAĞGÖRÜ","35":"SAYIKLAMA","36":"YALANLAMA","37":"DEKORCU","38":"ONLARSIZ","39":"KADINGÖBEĞİ","40":"BOĞULMAK","41":"DESENLİ","42":"ANTİPATİ","43":"İLAÇLAMAK"}