{"00":"ASABİYECİ","44":"YÜKSEKTEN","01":"ALIKOYMA","45":"HAFİYELİK","02":"GÖSTERGE","46":"MİZANPAJ","03":"SIFIRCI","47":"BALOTAJ","04":"FESLEĞEN","48":"BEŞPARMAK","05":"TAKABİLMEK","49":"BEKLETİLİŞ","06":"GÖRÜŞLÜLÜK","07":"ZEVKSİZ","08":"RENKLENDİRME","09":"BALIKSIRTI","50":"HARCAYIŞ","51":"IRGALAMAK","52":"PÜRÜZSÜZ","53":"MASKESİZ","10":"MUHAREBECİ","54":"VURULUVERMEK","11":"TENSİKAT","55":"İLGİSİZLİK","12":"KETUMİYET","56":"YIPRATILMAK","13":"ÇAPAKLANMA","57":"AKILLIM","14":"HURDALIK","58":"SAĞLAMA","15":"KAYGILI","59":"TAMİRHANE","16":"EZBERLEYİŞ","17":"YOLLATMAK","18":"ŞİZOFREN","19":"EŞİTLEŞME","20":"TUHAFINA","21":"RADİKAL","22":"DEĞERLENMEK","23":"VELESPİT","24":"TAŞIMACI","25":"PERDECİ","26":"SELİMLİK","27":"MÜKERRERLİK","28":"PUDRALAMA","29":"CURCUNAYA","30":"HAZIRLIKSIZ","31":"VAZGEÇİRMEK","32":"PARLAMA","33":"FAYDASIZLIK","34":"KAMUTAY","35":"ACISIYLA","36":"ZAPTURAPT","37":"GÜNLERDEN","38":"UĞURSUZLUK","39":"AŞIRMAK","40":"MEKTEPLİ","41":"İDAREHANE","42":"EHVENLİK","43":"SAATİNE"}