{"00":"ECİNNİLER","44":"ENTERNE","01":"VURDURMAK","45":"APOLİTİK","02":"ÇIKIVERMEK","46":"DİŞLEME","03":"YENİRCE","47":"GEDİKLERİ","04":"TEMİZLİKÇİ","48":"KURUMAK","05":"TAZELENMEK","49":"UYUŞMAK","06":"UĞULDAMA","07":"MUHTEŞEM","08":"TUTUŞMAK","09":"KAVURMACI","50":"SEÇMECİ","51":"MUSANNİF","52":"MEMURLUK","53":"BACAĞINA","10":"SÖNDÜRÜCÜ","54":"KAPİTÜLASYON","11":"SÖYLEMESİ","55":"ŞEFKATSİZLİK","12":"ABARTISIZCA","56":"KÜMELENMEK","13":"PAGANİZM","57":"KARDİYOLOG","14":"MANYETOMETRE","58":"KARANLIĞA","15":"DİKTACI","59":"KAFAKOL","16":"SORUNSAL","17":"BOHÇACILIK","18":"ENSESİNDE","19":"KÜSURLU","20":"MÜŞEVVEŞ","21":"FATURASINI","22":"CEKETİNİ","23":"YÜZÜNÜN","24":"TARZİYE","25":"CEREYANLI","26":"CÜSSESİZ","27":"SEYRELTME","28":"DÖRDERLİ","29":"KÖLELEŞTİRME","30":"ÇİLEKEŞ","31":"SAKLAMA","32":"BASINÇÖLÇER","33":"SOYUTLAMA","34":"GOLSÜZLÜK","35":"BÖLÜCÜLÜK","36":"HİDROSEFALİ","37":"ENJEKSİYON","38":"TAALLUK","39":"DEKORASYON","40":"KATALOG","41":"MÜLAYİM","42":"SAVAŞIM","43":"SENETLİ"}