{"00":"DEFTERDAR","22":"YERLEŞMEK","44":"KÖSTEKLEME","02":"GEZİNEBİLMEK","24":"UYDULAŞTIRMA","46":"BATILILAŞMA","04":"OLGUSALLIK","26":"RAHATLATABİLME","48":"REJİSÖRLÜK","06":"SÜBVANSİYON","28":"ÖRTÜŞTÜRMEK","08":"HİDROBİYOLOJİ","50":"TOPLAYABİLME","30":"ÖLÜMSÜZLEŞTİRME","52":"KOKAİNMAN","10":"NAKLEDEBİLMEK","32":"UYDURMACILIK","54":"DONANMASIZ","12":"TARTTIRMAK","34":"GURURLANMA","56":"KARNIYARIK","14":"KALITIMSAL","36":"YALNIZLAŞABİLME","58":"MAYALANIŞ","16":"AYRIMCILIK","38":"MUAYYENİYET","18":"KARAKTERİZE","40":"GİRİVERMEK","20":"BENİMSETTİRMEK","42":"BULUNDURABİLME"}