{"00":"DONDURMACILIK","22":"USTURUPLU","44":"KARANLIĞA","02":"FISTIKLIK","24":"HEDEFLEYEBİLME","46":"ÇIRPINTILI","04":"EREKLİLİK","26":"BAŞASİSTAN","48":"AKIMÖLÇER","06":"MORSALKIM","28":"HANÇERLENME","08":"MEDRESEYE","50":"BURACIKTA","30":"YAPABİLMEK","52":"ELEŞTİRMECİ","10":"KANATLANMA","32":"KÜÇÜMSEMEK","54":"VANTRİLOK","12":"KEDERLENME","34":"YANITLANMA","56":"KORPORASYON","14":"TAVERNACI","36":"GERİLİMSİZLİK","58":"DEBİMETRE","16":"ADAYABİLMEK","38":"AYRIŞTIRMA","18":"İŞLETİLEBİLME","40":"KURALCILIK","20":"RASYONALİTE","42":"ANAEROBİK"}