{"00":"TÜFEKÇİ","44":"KLOSTROFOBİ","01":"NAĞMELİ","45":"SİGARAYI","02":"EDEMEMEK","46":"YÖNELTMEK","03":"YOĞRULMAK","47":"HAYDARİ","04":"BAŞVURULMA","48":"PRATİSYEN","05":"İRTİCAL","49":"TORBADA","06":"SALDIRTMA","07":"GÖÇEBELİK","08":"HAVANIN","09":"KORKUTMACA","50":"SEYRETTİRMEK","51":"ÇİZGİLİ","52":"MİYOSEN","53":"FİİLİYAT","10":"YERKÜRE","54":"ASPİRİN","11":"HİDROTERAPİ","55":"SESSİZLİĞE","12":"GEREKSİNİM","56":"YALAYABİLMEK","13":"KATMERLİ","57":"SANDVİÇÇİ","14":"TABURCU","58":"SEVDALANIŞ","15":"ÇALIVERMEK","59":"OLUŞTURMAK","16":"DEĞİNMEK","17":"BÖLÜNME","18":"SÜLÜKLER","19":"TEFEKKÜRE","20":"SERSERİLİK","21":"TAZİYET","22":"ANİMATÖRLÜK","23":"KAYITLI","24":"GİRDİSİ","25":"SÜNDÜRMEK","26":"ÖĞRENEBİLMEK","27":"HAKKETMEK","28":"KAYGANLIK","29":"MÜSTERİH","30":"KİLİTLEME","31":"BÖĞÜRMEK","32":"SAHTECİLİK","33":"MADENSEL","34":"ÇILDIRASIYA","35":"DÜŞKÜNLEŞME","36":"DÖKÜLÜŞ","37":"SAPLAMA","38":"DELİRME","39":"TIRMALAMAK","40":"EYLEMSİ","41":"ÇOCUKSUZLUK","42":"YIKANMA","43":"ÇERÇEVELEMEK"}