{"00":"BATILILAŞTIRMA","22":"GEÇİNMEYE","44":"AKTARILMAK","02":"İLGİNÇLİK","24":"TRANSFORMASYON","46":"MUVAZAALI","04":"TEKNOLOJİ","26":"PARALELLİK","48":"MÜSRİFLİK","06":"MİSAFİRPERVER","28":"NOKTALANDIRMAK","08":"YATILILIK","50":"CEZALANDIRILMAK","30":"HEMENCECİK","52":"TEHLİKELİLİK","10":"PERVANELİ","32":"TUTUKSUZLUK","54":"DÖNEBİLMEK","12":"TRİPORTÖR","34":"ENTRİKACI","56":"PERVANESİZ","14":"MATEMATİK","36":"GELİŞİMCİLİK","58":"ÇEKİRDEKÇİLİK","16":"ADRENALİN","38":"AÇIKGÖZLÜLÜK","18":"BERRAKLIK","40":"YUTTURABİLMEK","20":"SERGİLENİŞ","42":"ERKEKSİLİK"}