{"00":"DİLEMEK","44":"KISKANDIRMAK","01":"BAĞIŞLAMAK","45":"SUÇİÇEĞİ","02":"FIRINLI","46":"TEKERLEKSİZ","03":"SEMAFOR","47":"ŞEFKATLİ","04":"HATIRLAYIŞ","48":"VETERİNER","05":"YAKLAŞIK","49":"GÖNDERİLMEK","06":"SAATÇİLİK","07":"DOKTORA","08":"YEMLENMEK","09":"MİLİLİTRELİK","50":"ORANGUTAN","51":"ÇEKİNMEK","52":"GENELKURMAY","53":"ORİJİNAL","10":"KIMILDATMA","54":"TOPLAMAK","11":"RADYOLOJİ","55":"SIRNAŞMAK","12":"BÜZÜLÜP","56":"YANILSAMA","13":"KIVRINTI","57":"GÜDÜMLÜLÜK","14":"SAPTAYABİLME","58":"ZEYTİNSİZ","15":"SATTIRMA","59":"BEYGİRLİ","16":"SOKAKTAN","17":"YIRTICILAR","18":"TANECİK","19":"DUYGULANMAK","20":"TEVERRÜM","21":"VÜCUDUNU","22":"TAHSİLLİ","23":"KÜFÜRLEŞMEK","24":"PEŞİNAT","25":"PORSELEN","26":"SİGARASIZLIK","27":"ESKORTLUK","28":"ÇAĞIRMA","29":"KİLİTLEMEK","30":"EŞEYSİZ","31":"ŞARTLANMAK","32":"KAFASINI","33":"ÇOCUKLA","34":"HÜCRELİ","35":"TUTULMAK","36":"FAYANSÇILIK","37":"SERPİŞTİRME","38":"POLİTİKACI","39":"NİSAİYE","40":"AŞILABİLME","41":"DOYURUCU","42":"BAŞLATILMAK","43":"KUMBARACI"}