{"00":"KOPARILIŞ","22":"ŞEREFSİZLİK","44":"BÖLEBİLME","02":"SENTAKTİK","24":"EBEGÜMECİ","46":"TATSIZLAŞMA","04":"BAĞIMSIZCA","26":"MODERNLİK","48":"GÖMEBİLME","06":"HATIRLATMA","28":"DERECELENDİRME","08":"FETİHNAME","50":"KARABORSACI","30":"DÜZENLEYEBİLME","52":"BAĞIŞLAMAK","10":"RİSKLİLİK","32":"GEÇİŞSİZLİK","54":"KOMPLEKSSİZLİK","12":"BULAŞIKÇI","34":"ELEŞTİRİLMEK","56":"TANIŞABİLMEK","14":"ENFLASYON","36":"HAYSİYETSİZLİK","58":"SARKIKLIK","16":"BASİTLEŞTİRMEK","38":"KULLANABİLME","18":"GEZGİNCİLİK","40":"AMAZONLAR","20":"HİDROKARBÜR","42":"ANAYASALLIK"}