{"00":"İSMETLİ","44":"İMZALATMAK","01":"TEDBİRLİLİK","45":"HAYVANİ","02":"SOYDURMA","46":"MODERATO","03":"ÇIRILÇIPLAK","47":"FİLİZKIRAN","04":"DEDELİK","48":"KAYGANLIK","05":"FIRKACILIK","49":"GICIRDATMA","06":"BİLEBİLMEK","07":"MÜTEŞEKKİR","08":"ANTİPATİK","09":"DEMİRLEME","50":"SOBACILIK","51":"HORMONAL","52":"PALYATİF","53":"KOPYACILIK","10":"DONUKLAŞMA","54":"YAKALAYIŞ","11":"SIĞLAŞMA","55":"FERAHLANMA","12":"SAMANLI","56":"ÇEKİŞMEK","13":"PEDOLOG","57":"ORUÇLULUK","14":"SAKINILAN","58":"KAFİYESİZ","15":"TERCİHEN","59":"MEYDANA","16":"ÇAĞRICI","17":"MEHTAPLI","18":"KIRKGEÇİT","19":"MUNTAZAMAN","20":"TOMBİLİK","21":"DİZİLEME","22":"MAHBUBE","23":"ÇIKIVERMEK","24":"TECEDDÜT","25":"YEĞLEMEK","26":"BEZENMEK","27":"ALTILIK","28":"SÜNNETLİK","29":"SEPETÇİ","30":"RETORİK","31":"ZÜPPELEŞME","32":"VANADYUM","33":"EĞRETİLİK","34":"OPORTÜNİST","35":"ÇEVİKÇE","36":"SAKARİNLİ","37":"KASITLI","38":"RENDELEME","39":"MECBUREN","40":"DÜŞESLİK","41":"BAHTİYAR","42":"KURUYASICA","43":"UMURSAMAK"}