{"00":"BOYLAMA","44":"ISIRABİLMEK","01":"BAŞKENTLİK","45":"RAPORCU","02":"ROKETATAR","46":"NİHAYETİNDE","03":"TOMBALAK","47":"BİTİRİLİŞ","04":"GÖNÜLLÜ","48":"KATEDEBİLME","05":"SONUÇLAMAK","49":"KAPICILIK","06":"İSTİRDAT","07":"ERKEKSİZ","08":"KOYDURTMA","09":"TARİHLİ","50":"ÇİSENTİ","51":"GÖZÜNDEN","52":"ÇARMIHA","53":"TANGIRTI","10":"ÇEVİRTTİRMEK","54":"ADALETİNE","11":"İNKIRAZ","55":"NEZAKET","12":"MÜCEHHEZ","56":"KADRANLI","13":"MURATLI","57":"KISKACI","14":"GÜLÜNME","58":"YİYECEK","15":"BİREYCİ","59":"POZİTİFLİK","16":"RAHİPLİK","17":"UYRUKSUZLUK","18":"AKSESUARCI","19":"MEHTABA","20":"PATATESÇİ","21":"ÇİFTLEŞMEK","22":"GÖZLERİNİ","23":"KATİYETLE","24":"İMPARATORLUK","25":"ÜSTÜNDEKİ","26":"SUSABİLMEK","27":"DELİBAŞ","28":"LEGALLİK","29":"MUKARRERAT","30":"AŞILATMAK","31":"FARKLILAŞMAK","32":"DARMADUMAN","33":"SAZCILIK","34":"ÇETİNLİK","35":"PEYNİRSİZ","36":"YENİLGİSİZ","37":"ETEĞİNDEN","38":"KAVLİNCE","39":"ARALARI","40":"ALGILAYICI","41":"SLOGANCILIK","42":"ÇEKEBİLME","43":"KENETLEME"}