{"00":"ESİRGEMEMEK","44":"ARALIKLI","01":"YÜZYILLARCA","45":"ISMARLANMAK","02":"COŞKUSUZLUK","46":"ENTERESAN","03":"KUKULETALI","47":"HERKESÇE","04":"KOTARMA","48":"SAATÇİLİK","05":"MAZOŞİST","49":"GEMLEMEK","06":"BANDROLSÜZ","07":"BAYİLİK","08":"KAYITTAN","09":"SAYGISIZLIK","50":"SENARYOCULUK","51":"BURNUNUN","52":"ATMOSFERİK","53":"ANIŞTIRMAK","10":"ÇALIŞABİLMEK","54":"BOYNUZLU","11":"PANAYIRCI","55":"KONTRATAK","12":"İFTARİYE","56":"YAŞLARA","13":"ZEVKİNDE","57":"YOĞURTÇU","14":"BELİRSİZCE","58":"YATAKÇI","15":"BİLEYİCİ","59":"EĞRİLİK","16":"MODELCİLİK","17":"FİZİKÇE","18":"KARŞILANMAK","19":"ŞEYTANİ","20":"BERTİLMEK","21":"GERDANLIK","22":"AĞIZDAN","23":"SEYRÜSEFER","24":"HÜVELBAKİ","25":"SANTRİFÜJ","26":"NARİNLİK","27":"DESTURSUZ","28":"TUTAMAK","29":"AVURTLARI","30":"AMETİST","31":"MUVAŞŞAH","32":"HASRETMEK","33":"KAŞIKLAMAK","34":"KAFAKOL","35":"LÜKSLÜK","36":"EYLEMEK","37":"MAHİRANE","38":"ISSIZCA","39":"ÖDENMEK","40":"SULBÜNDEN","41":"İŞTAHSIZLIK","42":"HAYLAZCA","43":"BİLİNÇLİLİK"}