{"00":"YÜZLEŞEBİLME","22":"ÇUKURLAŞMA","44":"BAŞARILMA","02":"YARARLANDIRMAK","24":"DUYURABİLME","46":"DEFTERİNİ","04":"SARHOŞLAŞMA","26":"TİTİZLENMEK","48":"BAHTSIZLIK","06":"FORMALİTECİ","28":"DÜŞÜRÜLME","08":"MEYHANECİDEN","50":"MEMLEKETSİZ","30":"YETMİŞİNE","52":"DÜMENCİLİK","10":"YAŞAYABİLME","32":"KESELEMEK","54":"ETİKETLENME","12":"TATMİNSİZLİK","34":"GURBETLİK","56":"KARTOGRAFİK","14":"PARTİLEŞMEK","36":"HESAPLICA","58":"GREKOROMEN","16":"PROPAGANDACI","38":"KAMPLAŞTIRMA","18":"AĞIRLATMA","40":"KAVRANILMAZ","20":"HİJYENİKLİK","42":"KATLETMEK"}