{"00":"AYIKLAMAK","44":"VATANDAŞ","01":"RÜTBELİ","45":"UĞULDAMA","02":"VURGUNCU","46":"AÇIKLATMAK","03":"DERKENAR","47":"KARARNAME","04":"ÇELİKLİ","48":"VANDALLIK","05":"ZIRILTI","49":"KAYTARMACI","06":"ZIDDINA","07":"DAVETÇİLİK","08":"YILDIZLAŞMA","09":"ŞAMATACI","50":"DİKLEŞMEK","51":"ELEKTRİKLEME","52":"KAHROLMA","53":"AĞAÇÇILIK","10":"YÖNELTİLME","54":"SİVRİLTMEK","11":"OTANTİKLİK","55":"ÇEKMECELİ","12":"FEDERALLEŞME","56":"GIDIKLANMAK","13":"ŞAPHANE","57":"PENCERECİK","14":"SUSTURULMA","58":"TALİHİNE","15":"VİSKOZİTE","59":"SAKINIMSIZ","16":"ÇÖZÜMSEL","17":"SÜREKSİZ","18":"DÖVÜŞTÜRMEK","19":"DERİŞİM","20":"TEKLİFSİZLİK","21":"SİLAHÇI","22":"TAHKİKAT","23":"FREKANS","24":"İSKANDİL","25":"SPORTMEN","26":"ÜZGÜNLÜK","27":"VASITALIK","28":"ÖNEMSİZLİK","29":"PAPAĞANLAR","30":"ALEGORİK","31":"MÜNHASIRAN","32":"NAZLANMA","33":"KURTULUŞSUZ","34":"İNSANLIKTAN","35":"GOYGOYCULUK","36":"BAHRİYELİ","37":"MÜBEŞŞİR","38":"SATTIRMA","39":"NUMARACI","40":"KOPYALANMA","41":"AMAÇSIZ","42":"UYGULANMA","43":"NALBANTLIK"}