{"00":"KATLANDIRMAK","44":"SAPTANMAK","01":"BENMERKEZCİ","45":"BANKAMATİK","02":"FERASETSİZ","46":"DELİRTME","03":"KALABALIKÇA","47":"ANLAYABİLMEK","04":"TOPARLACIK","48":"ÇİFTLEŞMEK","05":"YAKALANMAK","49":"İNANMAK","06":"ŞEKİLLENİŞ","07":"İŞLETMECİ","08":"YAĞMALANMA","09":"OFLAYIP","50":"DİASPORA","51":"KOZMOLOJİ","52":"ARKADAŞ","53":"OPSİYON","10":"ERİTİCİ","54":"EZBERCİ","11":"KILIĞINA","55":"EKONOMİST","12":"KOORDİNATÖR","56":"HABERCİLİK","13":"TERMONÜKLEER","57":"TÜNELİN","14":"OTLAKÇILIK","58":"ENDOKRİN","15":"TEŞKİLATLI","59":"ARALANMA","16":"AŞIRABİLMEK","17":"BİNBAŞILIK","18":"DÖVDÜRMEK","19":"GİYİNİP","20":"KAREKÖK","21":"ÇIKARTMAK","22":"KÜÇÜKLÜK","23":"TANIMLANMAK","24":"YANKISIZ","25":"MUHACİR","26":"YAFTALANMAK","27":"DEVİNİMSİZ","28":"DÖVMECİ","29":"KURTULUŞSUZ","30":"RAHATLIK","31":"DUYURUŞ","32":"BURKMAK","33":"TEMATİK","34":"HALLEDİLME","35":"REZİDANS","36":"AVROVİL","37":"RUHSATLI","38":"BİREYLİK","39":"GAYRİAHLAKİ","40":"ÇIKARABİLME","41":"KATILMA","42":"MAYONEZSİZ","43":"ASİLZADELİK"}