{"00":"İŞLEMEZLİK","22":"KIYABİLMEK","44":"ÇARPINTISI","02":"ANONİMLİK","24":"DEBELENİŞ","46":"SAKINCALI","04":"MUASIRLIK","26":"DAĞILABİLMEK","48":"BIRAKIVERME","06":"KUVVETSİZ","28":"ÖYKÜNMECİ","08":"TARAKLAMA","50":"SPEKÜLASYON","30":"AHİRETLİK","52":"BULDURMAK","10":"DENGELEYEBİLMEK","32":"ÇALIŞMACI","54":"SPİKERLİK","12":"GÖRMEZDEN","34":"PARAZİTOLOJİ","56":"İLİNTİSİZLİK","14":"PASPASLAMAK","36":"BAYILTILMA","58":"SAKINABİLMEK","16":"BİRAHANECİ","38":"GÜNLÜĞÜNE","18":"TEŞKİLATLANMAK","40":"AKSEPTANS","20":"YOĞUNLUKLU","42":"GELİŞKİNLİK"}