{"00":"BULAŞIKHANE","44":"KARATABAN","01":"KLASİSİZM","45":"FASULYEMSİ","02":"GURURSUZ","46":"LEVAZIMATÇI","03":"UMUTSUZLUĞA","47":"SERSEMLETMEK","04":"DAMARSIZ","48":"BAŞLIKÇI","05":"TASARIMLAMAK","49":"ONUNCULUK","06":"FARMASON","07":"ALDATMACA","08":"BELLETMEN","09":"BAŞYAPIT","50":"JİMNASTİKÇİ","51":"BAŞKENTLİK","52":"ÇAPALAMAK","53":"HAKARET","10":"UZATMALARI","54":"BULUNMAK","11":"MÜCAHİT","55":"YOĞURTLAMA","12":"UYUŞABİLME","56":"KENDİNİ","13":"BATAKÇILIK","57":"MESNETSİZLİK","14":"DÜZLEŞMEK","58":"VELİYULLAH","15":"ARMUDUN","59":"KAPLAMALI","16":"YAKARIŞ","17":"ÇETREFİLSİZ","18":"KAÇINDIRMA","19":"ESTETİKÇİ","20":"ÇİTİLEMEK","21":"ŞEHNAMECİ","22":"YILLANMAK","23":"ALKIŞLANMA","24":"SEDEFLİ","25":"KIRDIRTMAK","26":"SÜREBİLMEK","27":"PARTİLİLİK","28":"ÖNGÖREBİLMEK","29":"AĞIRLAMAK","30":"LİNOTİP","31":"KİMSENİN","32":"YARAYIŞLILIK","33":"KÖKLEŞMEK","34":"NECASET","35":"DERTSİZ","36":"COŞKULU","37":"RAPTİYE","38":"YETERLİLİK","39":"POLİKLİNİK","40":"İZİNDEN","41":"SELAMLIK","42":"TEKSTİLCİLİK","43":"TASARLAMA"}