{"00":"TERASLAMA","22":"UYDURABİLME","44":"PARAMETRELİ","02":"AYRANCILIK","24":"LEVAZIMAT","46":"KARAKEÇİLİ","04":"GÖRÜNÜŞLÜ","26":"AYRINTIYA","48":"ZIMBALATMA","06":"KAPILANMAK","28":"ÖFKESİZLİK","08":"KAVRAYIŞSIZLIK","50":"HAPSETMEK","30":"ÖZGÜRLEŞTİRME","52":"MAKYAJCILIK","10":"TELGRAFHANE","32":"PARMAKLAMAK","54":"ÇEKİRDEKLENME","12":"DERNEKÇİLİK","34":"ÖRTÜŞTÜRME","56":"KABARTMALI","14":"GIDAKLAMA","36":"KUDRETSİZLİK","58":"SAPTIRICILIK","16":"PAZARLAYABİLME","38":"MIRILDANMA","18":"KESKİNLİK","40":"ÖLÇÜSÜZCE","20":"PARÇALAYABİLMEK","42":"UYGULANIŞ"}