{"00":"ÇİFTLEŞMEK","44":"KOKLAŞMA","01":"ONLARINKİ","45":"KRONOMETRE","02":"GAZLANMA","46":"KONUŞMACI","03":"GÖRÜŞÜLME","47":"AMANSIZ","04":"FELAKET","48":"TURLAMAK","05":"KAPKAÇÇI","49":"TEFERRUATLI","06":"MÜNAKALAT","07":"SÖYLEYİVERME","08":"PİŞMANİYE","09":"DÜZMECİ","50":"ETRAFLI","51":"YAKIŞABİLMEK","52":"UYDURUKÇULUK","53":"HİLESİZ","10":"YEDİRME","54":"DÜŞESLİK","11":"KALDIRIMLARI","55":"BULANTI","12":"DAİRESELLİK","56":"TAHAMMÜLSÜZ","13":"YIRTILMAK","57":"POHPOHLAMAK","14":"MÜFTÜLÜK","58":"KOVULMA","15":"BEŞİKLİK","59":"PARILTI","16":"TİRENDAZLIK","17":"TANRISIZLIK","18":"GLİKOJEN","19":"DÖNÜMLERCE","20":"DİLLENDİRİŞ","21":"DEFNEDİLMEK","22":"SAYAÇLI","23":"BAKLİYAT","24":"ASFALTLAMA","25":"SAĞDUYULULUK","26":"YEMEKHANE","27":"VERGİLEMEK","28":"KRALDAN","29":"SELAMETE","30":"GERDİRMEK","31":"YAZILMA","32":"BEKLENME","33":"SEBZELİK","34":"KOLTUKLAMAK","35":"ÜSLENME","36":"EMZİRMEK","37":"DİŞİSEL","38":"BAĞIRABİLMEK","39":"BAŞSIZLIK","40":"TUTARAK","41":"IRAKLAŞMAK","42":"YÖNELİK","43":"SÖZCÜLÜK"}