{"00":"DOKTORLUK","44":"TOMOGRAFİ","01":"KUZULAMA","45":"CAHİLLEŞMEK","02":"RESEPTÖR","46":"KAMANÇO","03":"CANLANDIRMA","47":"AKLİYAT","04":"ÜSLUPÇU","48":"HEYECANSIZ","05":"KADROLU","49":"BAĞIŞLANMA","06":"SARMALAMAK","07":"ESNEYEBİLME","08":"KAMBERSİZ","09":"YUMUŞAKÇALAR","50":"KEYFİNİ","51":"BASAMAKSIZ","52":"CERAHAT","53":"KELİMELERİ","10":"ÖYKÜNMECİLİK","54":"DELİRTMEK","11":"DALALET","55":"MÜZİSYENLİK","12":"İÇLENME","56":"AĞDALILIK","13":"TABİİLEŞME","57":"ÇALIŞMA","14":"YARGILANIŞ","58":"KAPMACA","15":"KILGISAL","59":"POLEMİKÇİLİK","16":"PSİKİYATRİ","17":"YARIŞMAK","18":"DESTELEME","19":"MISIRCI","20":"ÖRTÜŞTÜRMEK","21":"DİSKJOKEY","22":"KATALOG","23":"PİŞİRİLME","24":"DUYURMA","25":"RUHUNDA","26":"DEKORCU","27":"KOMBİNA","28":"HAFIZIKÜTÜP","29":"TAKINAK","30":"HAVSALASI","31":"ERTELETMEK","32":"DARALMA","33":"EVCİMEN","34":"USLANMA","35":"DAMARCIK","36":"GÖBEKSİZ","37":"FAYTONCU","38":"İSTİDATLI","39":"BOŞANABİLMEK","40":"POLEMİKÇİLİK","41":"İDMANSIZLIK","42":"BİTİŞİKLİK","43":"İHTİLAFA"}