{"00":"YATABİLMEK","22":"LİMNOLOJİ","44":"KÜRKÇÜNÜN","02":"REKLAMCILIK","24":"ASFALTLAMA","46":"TIRMALAYIŞ","04":"GÖSTERİLMEK","26":"YAKLAŞMAK","48":"BETİMLENME","06":"MİNARESİZ","28":"KURUMLANMA","08":"UYUŞTURMA","50":"SOLUCANLAR","30":"ŞÜKRETTİRME","52":"BİLEĞİNİN","10":"TOPRAKLANDIRMA","32":"İSPERMEÇET","54":"ATILABİLME","12":"ÇÖZÜMLEYEBİLMEK","34":"DİKİZLENMEK","56":"BATERİSTLİK","14":"KAZANIRSAN","36":"CERAHATLİ","58":"BULAŞTIRMA","16":"ADEMİMERKEZİYET","38":"İSTİFLENİŞ","18":"KRONOLOJİ","40":"YEDİRTMEK","20":"MALİYECİLİK","42":"İZLENİMCİLİK"}