{"00":"TANITICI","44":"KARABATAK","01":"YANITLANIŞ","45":"ROTATİF","02":"KEŞFEDİLMEK","46":"GİDERMEK","03":"DİKDÖRTGEN","47":"RANTABL","04":"EKMEKÇİLİK","48":"PARASINI","05":"TOSTÇULUK","49":"AFYONUNU","06":"ÇARŞAMBA","07":"ÖĞRENEBİLME","08":"AKITABİLMEK","09":"PATATESÇİ","50":"SAKATATÇI","51":"KARAKTER","52":"OTÇULLAR","53":"MESABESİNDE","10":"TAKINAKLI","54":"BİREYCİLİK","11":"VOLTAYA","55":"İDDİALI","12":"MASALSI","56":"KAZANDIRMAK","13":"DERLEMECİLİK","57":"ŞUURSUZ","14":"KADINCIL","58":"TANTANA","15":"METOTLU","59":"AÇIKLANAN","16":"ÖFKELENME","17":"PARANTEZ","18":"ENTELEKT","19":"ZORLAYICILIK","20":"ABARTISIZLIK","21":"HAKÇASI","22":"BİSTURİ","23":"PORTBEBE","24":"BAĞIRTI","25":"VURUŞMAK","26":"KIVILCIM","27":"UMURSAMAZ","28":"BAKALIM","29":"TEKELLEŞMEK","30":"YUVARLAKLIK","31":"TARTAKLANMA","32":"HIYARAĞASI","33":"TURLAMAK","34":"AĞLATAN","35":"KORUTMAK","36":"KONUŞLANMA","37":"DEVRİLME","38":"KÖŞESİZ","39":"VARSILLIK","40":"MÜYESSER","41":"TALİHSİZLİK","42":"DARILMAK","43":"KINACIK"}