{"00":"BORÇLANDIRILMAK","22":"ARATTIRMAK","44":"PALAZLANMAK","02":"ANIŞTIRMAK","24":"KAPİTALİSTLEŞME","46":"SONLANDIRIŞ","04":"MADERŞAHİ","26":"HÜZÜNLENME","48":"AVANTASIZ","06":"GÖRKEMLİLİK","28":"İSTİFÇİLİK","08":"İLANCILIK","50":"DEĞİŞTİRTMEK","30":"KONJONKTÜR","52":"AĞRISIZLIK","10":"MÜDAHİLLİK","32":"ÇELMELENME","54":"KÖRÜKLENMEK","12":"MAHPUSLUK","34":"YARAMAMAK","56":"BARINDIRABİLME","14":"KAPATABİLMEK","36":"METAFİZİKÇİ","58":"BAŞDANIŞMANLIK","16":"İKTİDARSIZ","38":"ALIŞKINLIK","18":"MUKTEDİRLİK","40":"YIKABİLMEK","20":"GEVŞETEBİLMEK","42":"ÇABALAMAK"}