{"00":"KORUTMA","44":"BENZERLİK","01":"TARAFSIZLIK","45":"PESTENKERANİ","02":"YALAKALIK","46":"ZEHİRLEMEK","03":"MELEZLEME","47":"YALINLIK","04":"ROMANLAŞMA","48":"TIPKISI","05":"BAŞBAYİ","49":"KAYNAMA","06":"KARINCASIZ","07":"BAĞIRMAK","08":"ELEMANSIZ","09":"TAKSİCİ","50":"SEFERLİK","51":"KOYNUNDA","52":"NETLEŞME","53":"KESELENMEK","10":"ZAHİREN","54":"HELALLEŞMEK","11":"ŞIRAKKADAK","55":"AYAKLARININ","12":"İSTİRDAT","56":"MODELİST","13":"İŞPORTA","57":"SAHİDEN","14":"İDEALSİZLİK","58":"KAPAKLANMA","15":"TARIMSAL","59":"SANSASYON","16":"KAYITSIZLIK","17":"ACINDAN","18":"CİYAKLAMAK","19":"KUŞKULU","20":"ABDESTSİZ","21":"NÜMAYİŞÇİ","22":"APAÇIKLIK","23":"TAZELENİŞ","24":"RENDELEMEK","25":"DEMODELİK","26":"OYUNLAŞTIRMA","27":"OLDURTMA","28":"CESAMETLİ","29":"BOĞAZLAMAK","30":"KAPLAMAK","31":"DİKLEŞMEK","32":"MEMNUNLUK","33":"DUYULUR","34":"SPESİYALİTE","35":"AŞAĞILANMAK","36":"KOMEDYEN","37":"GLADYATÖR","38":"UZAKLARA","39":"KÖRELTME","40":"PERMİYEN","41":"ANNELİK","42":"POLARİMETRE","43":"EĞİTİCİLİK"}