{"00":"YAVANLAŞMA","44":"ÖLDÜRÜLMEK","01":"DÜRTÜLMEK","45":"YABANCILAMA","02":"VERESİYE","46":"KULLANABİLME","03":"GENİŞLETİLME","47":"PELİKÜL","04":"SATAŞMA","48":"SÜPÜRTME","05":"TAVUKÇU","49":"BEDDUASI","06":"ÇIĞIRTMA","07":"YUSYUVARLAK","08":"HİGROMETRE","09":"KENTLEŞME","50":"TAFRACI","51":"KLONLAMA","52":"PATOLOJİ","53":"ÇOCUKÇA","10":"TAZYİKLİ","54":"BÜYÜLTEÇ","11":"SALAMURALIK","55":"İRDELENMEK","12":"KOKARTLI","56":"BAŞEFENDİ","13":"PÜRİTEN","57":"DANIŞIK","14":"GÖZAYDIN","58":"FUTBOLCU","15":"YÖNETİLME","59":"BAŞARABİLMEK","16":"KARŞIDAN","17":"AĞZINDA","18":"İŞKİLLİ","19":"DANSSIZ","20":"YİTİRİLMEK","21":"AKSİYOM","22":"PRATİSYEN","23":"BÜTÜNLEŞİK","24":"KAVMİYETÇİ","25":"POMPALANMAK","26":"NEVALEYİ","27":"ZIDDINA","28":"DEĞİNMEK","29":"TUTUMSUZLUK","30":"HARMANI","31":"GÖÇEBİLMEK","32":"PARABOLİK","33":"YEŞERTİ","34":"PASTÖRİZE","35":"DADANMAK","36":"BASTONLU","37":"ODUNCULUK","38":"RUHSALLIK","39":"LİMNOLOJİ","40":"KALANDIR","41":"PERUKÇU","42":"HESAPLANMAK","43":"MÜHTEDİ"}