{"00":"EGZOTİK","44":"SİNEMASEVER","01":"KULAĞINA","45":"HELMİNTOLOJİ","02":"TARIMCI","46":"ETTİRGEN","03":"GÖRKEMSİZ","47":"YALITIMLI","04":"YENDİRME","48":"İSTİFADE","05":"BÖREKÇİ","49":"İŞLEVSİZ","06":"ÇELİŞMEK","07":"EKLEMLENME","08":"HOROZGÖZÜ","09":"YİTİRME","50":"KOLEKTİVİZM","51":"USTURAYI","52":"ARKASIZLIK","53":"COŞKUSUZLUK","10":"MUHTEREM","54":"HAYALİNDEN","11":"KESKİNLEŞMEK","55":"TELESİYEJ","12":"ÇALKALAMA","56":"YIKTIRILMAK","13":"MÜZELİK","57":"DAYANILMAK","14":"KONÇSUZ","58":"DUBARACI","15":"MERKEZCİ","59":"KONTROLÖRLÜK","16":"LEHİMCİ","17":"HAVAİYAT","18":"SARIHALİLE","19":"SAĞALTICI","20":"LAĞIMCI","21":"LÜZUMLU","22":"MAHMUDİYE","23":"HAFRİYATÇI","24":"ÇEPERLİ","25":"KARATABAN","26":"MUADİLLİK","27":"DENKLEŞTİRME","28":"KORUNGA","29":"ARANABİLMEK","30":"KUDRETTEN","31":"SÖMÜRTMEK","32":"TIRPANDAN","33":"PORSİYON","34":"İNATLIK","35":"HİDROLİZ","36":"İZLETİLME","37":"AŞAĞILATMAK","38":"KADINSALLIK","39":"İSTİHKAR","40":"KARTELLEŞME","41":"STRATUS","42":"EVLENME","43":"DOLAMBAÇSIZ"}