{"00":"YAVANLAŞMA","22":"BELİRSİZLEŞME","44":"GECİKMİŞLİK","02":"TÜRBEDARLIK","24":"MÜNECCİMBAŞI","46":"BİRLEŞTİRMEK","04":"BIRAKILIŞ","26":"DALDIRMAK","48":"KOPYALAYABİLMEK","06":"MEVSİMLİK","28":"SEMİYOLOJİ","08":"OTORİTESİZLİK","50":"ATILABİLMEK","30":"KUMAŞÇILIK","52":"ERGİNLEŞME","10":"ŞİŞİRİLME","32":"DİREKSİYON","54":"SÖMÜRÜCÜLÜK","12":"KÖTÜCÜLLÜK","34":"İZNİNİZLE","56":"ÇALIŞKANLIK","14":"KAPAKLANMA","36":"DİLENCİLİK","58":"SAĞLIĞINDA","16":"SEVİNÇSİZ","38":"HEVESLİLİK","18":"KALDIRABİLME","40":"ÖRDEKBAŞI","20":"CANSIZLIK","42":"TEHLİKEYE"}