{"00":"ÇARPIKLIK","44":"YERLEŞME","01":"REFLEKTÖR","45":"SİLAHLIK","02":"HAKSIZCA","46":"KÜLYUTMAZ","03":"KADAYIF","47":"DALGALANIŞ","04":"ÖLDÜRÜLMEK","48":"DENETTİRMEK","05":"İÇTENLİKLİ","49":"TERMİTLER","06":"ÇIKILMAK","07":"ÜZÜNTÜLÜ","08":"YAĞMALAMA","09":"ABUKLUK","50":"MANTARLAMAK","51":"ARITILMA","52":"MÜRŞİTLİK","53":"DENEYLEMEK","10":"ALBÜMİN","54":"ŞİŞMANLIK","11":"UZANMAK","55":"KURTARIM","12":"BUĞDAYIM","56":"TAŞABİLMEK","13":"HARDALLIK","57":"İSPATLAYIŞ","14":"PERÇEMLİ","58":"MARKALAMA","15":"FUKARANIN","59":"GELECEK","16":"ÇÜRÜTEBİLMEK","17":"TUTUNABİLME","18":"BEREKETLENME","19":"KAHROLSUN","20":"TAAŞŞUK","21":"İTİRAZCILIK","22":"FALAKASIZ","23":"METEOROLOG","24":"ÖZELLİKLİ","25":"MUAYYEN","26":"MELANET","27":"YILANCIK","28":"BESTELİK","29":"TAMAMEN","30":"VİTESLİ","31":"ALTMIŞARLI","32":"EVCİLER","33":"SERÜVENCİLİK","34":"SOYDAŞLIK","35":"ALIŞKAN","36":"FÜTUHATÇI","37":"ALGILAMAK","38":"FAZLACA","39":"AYNIYLA","40":"DÜŞMANIN","41":"GURBETE","42":"OLMUŞLUK","43":"TARÇINLI"}