{"00":"FARKLILAŞMAK","44":"BÖLÜNEBİLME","01":"MEVZİLENME","45":"ÇATIŞMAK","02":"SIÇRAMAK","46":"KUŞKUSUZ","03":"BÜSBÜTÜN","47":"KOLEKSİYON","04":"HEKTOLİTRE","48":"KAÇILMAK","05":"DİLENCİ","49":"YÜREKLİLİK","06":"TANSİYONU","07":"EKİCİLİK","08":"RADİKALLEŞME","09":"TASLAMA","50":"KÖŞESİZ","51":"TAKSİRAT","52":"MANTARLAMAK","53":"MÜHÜRLENİŞ","10":"FABRİKACI","54":"SUBAYLIK","11":"DÖNÜMLERCE","55":"İPOTEĞİ","12":"SİLECEK","56":"ANTİSEMİT","13":"FONKSİYON","57":"DÖTERYUM","14":"NARSİSİZM","58":"SİNARİT","15":"MÜDAVİM","59":"NESNELLİK","16":"OKŞATMA","17":"ÖNLENME","18":"KATLETMEK","19":"DEVAMSIZLIK","20":"KANIKSATMA","21":"HANIMCIK","22":"KURTULMALIK","23":"DÖVMELİ","24":"ZATÜRRE","25":"SAVUNMALI","26":"ATILIMCILIK","27":"KORAMİRAL","28":"TEHDİTLİ","29":"MÜCEVHERCİ","30":"TERBİYESİNİ","31":"KUSABİLMEK","32":"AYRILMAK","33":"MUAMELAT","34":"BADANACI","35":"SPESİFİK","36":"HOŞLAŞTIRMA","37":"DAYANIKLI","38":"KIYAFETNAME","39":"TANITMAK","40":"KÖRÜKLENME","41":"DİVANHANE","42":"KIYAFETNAME","43":"ÖĞRETİM"}