{"00":"YAVANLIK","44":"GÖRKEMLİLİK","01":"ALAKARGA","45":"AHLATIN","02":"SEVECEN","46":"TOHUMLUK","03":"SEVİYELİ","47":"CİLTLİK","04":"İNDİRİMLİ","48":"BOĞMACA","05":"MÜRTEFİ","49":"BULMACA","06":"BURJUVAZİ","07":"HAREKELİ","08":"ÇIKARILIŞ","09":"HATMETME","50":"YİNELEMELİ","51":"KONUŞMAYA","52":"UYARICI","53":"DÖNÜŞMEK","10":"GEVŞETİLMEK","54":"TEŞEKKÜL","11":"SABIKALI","55":"BAŞKOMUTAN","12":"KURSİYER","56":"DRAMATİZE","13":"DOLOMİT","57":"BOŞLAMA","14":"TERSLEME","58":"HAMAMLIK","15":"AMELİYATHANE","59":"TURŞULU","16":"İMZASIZ","17":"ESTİRME","18":"TAHTALIKÖY","19":"YALPALAMAK","20":"SENETSİZ","21":"TARAKLILAR","22":"LİBERAL","23":"ADAMCIL","24":"GELİŞİMCİLİK","25":"GÜRLEYİP","26":"ARATTIRMA","27":"EDİLGENLİK","28":"MEKTEPLİLİK","29":"MEZBAHA","30":"ATFEDEBİLMEK","31":"KAYNAMAK","32":"DERİŞTİRME","33":"TAPYOKA","34":"SAKARİNLİ","35":"MANİKÜRLÜ","36":"ÇARŞAFÇI","37":"ANLAYALIM","38":"HARHARYAS","39":"ORDUEVİ","40":"ÖDENEKSİZ","41":"FELSEFİ","42":"ZULMETME","43":"PEKİŞMEK"}