{"00":"MEZHEPÇİ","44":"HUMBARA","01":"DİNDARLAŞMAK","45":"DOSTLAR","02":"DİFTERİ","46":"CİSİMLEŞMEK","03":"YIKATMAK","47":"HAKSEVERLİK","04":"GARDİYANLIK","48":"ANLAMCA","05":"AKREDİTİF","49":"DAVETSİZ","06":"BÜYÜKLÜK","07":"BEZGİNLİK","08":"HİSSİYAT","09":"BUNALTMAK","50":"SİNEMACI","51":"LEZZETLİ","52":"GÜLÜNME","53":"DİREKÇİ","10":"YAMULMA","54":"ALEYHTE","11":"PARASIZ","55":"TÜFEKÇİLİK","12":"AKINTILI","56":"ENDİŞELENME","13":"SATILABİLMEK","57":"BATIRMAK","14":"FIRINCI","58":"HOCALAR","15":"YANILGIYA","59":"İŞTİRAK","16":"MÜHTEDİLİK","17":"KAŞIKÇI","18":"İFADELİ","19":"KORUNMAK","20":"YIĞILIP","21":"MÜNAKAŞALI","22":"İYONLAŞMA","23":"YEŞİLLİ","24":"NAZİRSİZ","25":"KANDIRABİLME","26":"SOKABİLMEK","27":"KARAKTERLİ","28":"LEBLEBİCİ","29":"DAYAKLIK","30":"FIRLATMA","31":"AMAÇLANMAK","32":"MEŞRULAŞMAK","33":"CANLANMA","34":"SUNABİLMEK","35":"KURABİYECİ","36":"EVLATLI","37":"TEBEŞİRLİ","38":"BOĞAZLAŞMA","39":"TÜKÜRMEK","40":"ZEVKİNDE","41":"DOSYASI","42":"ANKETÖR","43":"AKAMETE"}