{"00":"ÇİĞNEMLİK","44":"SOĞRULMA","01":"KAZIKLANMAK","45":"EMEKLİYE","02":"SAFAHAT","46":"SANRILAMA","03":"ÇİÇEKLEMEK","47":"TANILAMAK","04":"MÜNTESİP","48":"SARIKIZ","05":"KUSTURMAK","49":"FİLARMONİK","06":"FEVKALADELİK","07":"TEKELLEŞME","08":"FİLOTİLLA","09":"BÖCEKLENME","50":"DEPOZİTO","51":"ULAŞILMA","52":"BAŞÖRTÜLÜ","53":"TEKERLİ","10":"HAPSETME","54":"İLTİBASA","11":"İÇLENİŞ","55":"VAHŞİCE","12":"DANGALAKLIK","56":"ŞIRINGA","13":"AYAKLIK","57":"BİLİNCİNE","14":"SÜRÜKLENME","58":"HAÇVARİ","15":"DUYUMSAMAK","59":"AĞLAŞMAK","16":"BOŞALIM","17":"HELMİNTOLOJİ","18":"GELECEKÇİ","19":"GANİMET","20":"YARATABİLME","21":"ÇENGELLEME","22":"KAPISIZLIK","23":"EKONOMİZM","24":"TARİFELİ","25":"ŞANGIRTI","26":"CİĞERİMİN","27":"OTURMUŞLUK","28":"VERANDA","29":"KABALAŞMAK","30":"BOZKIRLI","31":"KÖMÜRCÜLÜK","32":"BUCAKSIZ","33":"İNDİKATÖR","34":"TEMBİHLİ","35":"KÖTÜCÜLLÜK","36":"DERTLENMEK","37":"İŞİTTİRMEK","38":"ÇAĞRIŞTIRMA","39":"DİYABET","40":"GELİŞME","41":"ÖLÇÜMLEME","42":"HİPOTEZ","43":"DEVREYE"}