{"00":"KALUBELADAN","44":"YELLENMEK","01":"BAVULLU","45":"KOLUNDA","02":"YAPTIĞI","46":"YUSUFÇUK","03":"GURULTU","47":"HASSASİYETLİ","04":"HIRSLANDIRMA","48":"GALATIMEŞHUR","05":"BİLİMSİZLİK","49":"İŞİTTİRMEK","06":"SÖYLEME","07":"HİTABEN","08":"KOLAYLAŞMAK","09":"SİYASALLIK","50":"BİBERLİ","51":"TAYFÖLÇER","52":"NEFSİNE","53":"DİRİLTMEK","10":"SEVİNÇLİ","54":"TANITIŞ","11":"SÜMÜKSÜ","55":"BAĞRINA","12":"TRENÇKOT","56":"KAÇIŞMAK","13":"KORGENERAL","57":"MAHLUKAT","14":"TAHVİLAT","58":"SEKİZGEN","15":"BİRİMLER","59":"AYRIKSI","16":"AYRIMCILIK","17":"SOFİSTİKE","18":"TEKLEŞME","19":"ISINMAK","20":"BİLEYİCİLİK","21":"LOSTROMO","22":"ŞARTLANMA","23":"AÇILABİLMEK","24":"BAŞÇAVUŞ","25":"BİYOGRAFİK","26":"YARATICILIK","27":"SAĞABİLMEK","28":"ÇAĞIRMA","29":"KALLEŞÇE","30":"YANILTICI","31":"KEMİKSİZLİK","32":"ÇARPINTISI","33":"YUTKUNMA","34":"ÜSTÜVANİ","35":"ZEVKTEN","36":"PUANLANDIRMA","37":"KEYİFSİZ","38":"ERTELETTİRME","39":"ORANSIZ","40":"TOPARLANMA","41":"AZİZLİK","42":"HAYSİYETLİ","43":"BAKIMSIZLIK"}