{"00":"BALIKHANE","44":"ÖNEMSENME","01":"TASARIMLI","45":"BALONCULUK","02":"MEŞALECİ","46":"TABANLI","03":"TOSLAMA","47":"ANASONLU","04":"DÜMENDEN","48":"İNSANCI","05":"ÇATIVERMEK","49":"ESNETEBİLME","06":"KOŞABİLME","07":"DEMİRLEME","08":"SAKATAT","09":"GÖSTERİCİLİK","50":"KUYRUKSUZLAR","51":"SOKTURMAK","52":"KORKUTMA","53":"KOLOKYUM","10":"BİGÜNAH","54":"TASAVVUFİ","11":"ÖNCÜLÜK","55":"POTURLU","12":"MAKASSIZ","56":"AHENKSİZLİK","13":"HAFRİYATÇI","57":"BEZEMECİLİK","14":"ÇAKILIP","58":"PRODÜKSİYON","15":"TEVERRÜM","59":"İŞTİGAL","16":"MEMECİK","17":"KURTARICILIK","18":"İNCELENMEK","19":"GAYRİNİZAMİ","20":"BUYURGANCA","21":"MAHSUSTAN","22":"ÇEKEBİLME","23":"DENGECİLİK","24":"TANINABİLMEK","25":"KAYDEDİLME","26":"USTURMAÇA","27":"ATLETİZMCİ","28":"ISSIZLAŞMA","29":"ÇALINIŞ","30":"AZARLANMA","31":"DİKİŞİNİ","32":"YARATIŞ","33":"SUALSİZ","34":"YÜCELİŞ","35":"BEYAZIMTIRAK","36":"KALORİFERSİZ","37":"DOLAPÇI","38":"UZAKLAŞTIRMA","39":"HAMAKAT","40":"EZBERLETME","41":"BAĞIRMAK","42":"KARDIRMA","43":"VARTAYI"}