{"00":"ÇİZMEDEN","44":"BİBERCİ","01":"ÇIKARCI","45":"HOPARLÖRSÜZ","02":"LAĞIMCI","46":"BİHAKKIN","03":"FOSFATSIZ","47":"TERAZİYE","04":"KAYNAKLANMAK","48":"DERİNLEŞMEK","05":"ALDIRILMAK","49":"BOĞAZLANMA","06":"SÜRDÜRME","07":"TROMPET","08":"TARİKATÇILIK","09":"YALNIZCILIK","50":"TESADÜF","51":"MÜTEHAVVİL","52":"VAROLUŞ","53":"FERAHNAK","10":"KÖKLEŞTİRMEK","54":"SANILMA","11":"EZGİSEL","55":"İNTİHAL","12":"AYDINLI","56":"PAYLAŞABİLME","13":"MÜVEKKİLE","57":"KÜÇÜKLÜ","14":"VATANSIZLIK","58":"KÖRLEŞME","15":"KATILAŞMA","59":"ÇAMAŞIRCILIK","16":"ÇATIŞMACILIK","17":"DİREMEK","18":"KIVRANMAK","19":"UYGULANMAK","20":"ELLENMİŞ","21":"KÜTLETME","22":"PEYGAMBER","23":"KEÇİNİN","24":"KEMİKLERİNİ","25":"CÜSSESİZ","26":"TOSTOPARLAK","27":"MENSUPLUK","28":"KİFAYETLİ","29":"İMTİYAZLILIK","30":"AKILDAN","31":"COPLATMA","32":"KOYULAŞMA","33":"GARSONİYER","34":"KÖFTEHOR","35":"TAHAMMÜR","36":"DELİLLİ","37":"KORPORATİF","38":"ANTRAKT","39":"DEDİRTMEK","40":"TEPESİNDE","41":"YANAĞINDAN","42":"SİRKÜLER","43":"PELTELEŞME"}