{"00":"POSTAYA","44":"İRREDANTİZM","01":"HİSTOLOJİ","45":"ŞÖVALYELİK","02":"TÜMLEŞİK","46":"TERTİPÇİLİK","03":"YILDIZSIZ","47":"BAKABİLME","04":"KEMENÇECİ","48":"DEFTERHANE","05":"DAYIZADE","49":"SORGULATMAK","06":"BURJUVAZİ","07":"HAVALARA","08":"KOMEDYEN","09":"ŞEHİRCİLİK","50":"HORTUMLU","51":"DÜMENCİ","52":"SİYASAL","53":"UMURSAMA","10":"TAPTAZE","54":"ÖNCELERİ","11":"DERECEYE","55":"TAACCÜP","12":"DAYATMAK","56":"ASABINA","13":"KLAVYELİ","57":"SIKIŞMA","14":"KIVAMINI","58":"ÖNCELEMEK","15":"İHTİYATEN","59":"EĞRİLİK","16":"BAĞIMSIZCA","17":"AYRANIM","18":"DOĞALLIK","19":"ERBAŞLIK","20":"KARASAKIZ","21":"DEVİNİŞ","22":"SOLÜSYON","23":"NAHOŞLUK","24":"BİLİŞSEL","25":"KINASIZ","26":"NİYETLENMEK","27":"FARFARA","28":"DÜĞÜMLÜ","29":"ALDATILMAK","30":"ÜYELİĞİ","31":"ADAPTÖR","32":"PAZARCILIK","33":"HIRILTILI","34":"AZDIRILMAK","35":"İNDİRMEK","36":"BİÇİMLEMEK","37":"MAZLUMLUK","38":"DEĞİŞTİRİŞ","39":"HAVUZCU","40":"TEKLEŞME","41":"ODUNCULUK","42":"ALEYHTAR","43":"TOPRAKLAMAK"}