{"00":"SUBJEKTİFLİK","22":"YALINLAŞTIRMAK","44":"SINIFLAŞMA","02":"ARTTIRTMAK","24":"BUHURUMERYEM","46":"KOPARTABİLME","04":"KAMBURLUK","26":"PANTOLONLU","48":"DARÜLACEZE","06":"ÇALIŞTIRMAK","28":"DİSTRİBÜTÖR","08":"ETTİREBİLME","50":"TARTIŞMALI","30":"DERTLEŞMEK","52":"KEŞİŞLEME","10":"EZİLMİŞLİK","32":"KURTULUŞSUZ","54":"KOŞUŞTURMA","12":"HÜRRİYETSİZLİK","34":"AYRICALIKSIZ","56":"SAKATLAMAK","14":"DOĞURABİLMEK","36":"BİLARDOCU","58":"SAYACILIK","16":"DERİNLEŞTİRMEK","38":"ULTRAMODERN","18":"TÖRPÜLENME","40":"YAĞDANLIK","20":"PAHALILAŞTIRMAK","42":"FARKLILIK"}