{"00":"İŞKENCECİLİK","44":"MÜSTACEL","01":"GENLEŞMEK","45":"DÜZGÜNCÜ","02":"TUĞRAKEŞ","46":"DAYANILMAZ","03":"ZAHİRDE","47":"İSTATİSTİKÇİ","04":"AVUÇLAMAK","48":"ÇALDIRAN","05":"ÖDETİLME","49":"SEMİZOTU","06":"KUNDAKLAMA","07":"ORGANZE","08":"KLİŞELEŞMEK","09":"EZEBİLMEK","50":"BAHSEDEBİLME","51":"İSPRİTİZMA","52":"YASTIKLI","53":"FIRÇALAMA","10":"BUĞDAYGİLLER","54":"KISKIVRAK","11":"YÜKLENİLME","55":"TEMİZLİKÇİ","12":"SERSERİ","56":"ÇUKURLAŞMA","13":"BINGILDAK","57":"ÇELİŞİKLİK","14":"ODAKLAYICI","58":"AŞICILIK","15":"CEBELLEZİ","59":"HERCÜMERÇ","16":"KUVVETİNİ","17":"EGZOTİK","18":"GÜZELİM","19":"YAPMACIKSIZ","20":"TAHATTUR","21":"ÇALTILIK","22":"YILLARCA","23":"GUSÜLHANE","24":"DİLCİLİK","25":"KUMLAMA","26":"KİRALANMAK","27":"TÜREYİŞ","28":"TEMSİLCİ","29":"MÜBALAĞASIZ","30":"KENARSIZLIK","31":"BURADAN","32":"ELİMİNE","33":"MANTARLAMAK","34":"MASKARA","35":"KONSOLİT","36":"ASABİYECİ","37":"ZINDIKLIK","38":"İHTİYAR","39":"SİNEMACILIK","40":"PEDİKÜRCÜ","41":"SİFONLAMA","42":"AÇIKLAMA","43":"KARBÜRATÖR"}