{"00":"TAHTAKURUSU","44":"KIPIRDAYIŞ","01":"UYGUNSUZLUK","45":"YAKIŞIK","02":"KİTAPÇA","46":"YAPTIĞI","03":"VURDURTMAK","47":"EFSUNLU","04":"VAKTİNDE","48":"POSASINI","05":"BİLLURİYE","49":"DÜZENBAZ","06":"TAKSİTE","07":"İLAÇSIZ","08":"KİSVEYE","09":"ISIRABİLMEK","50":"KATBEKAT","51":"MİHNETSİZ","52":"MUHAYYİLE","53":"HALICILIK","10":"RANDIMAN","54":"TOLERANSSIZ","11":"BUNALTMA","55":"BAYILTILMAK","12":"AÇIKLAR","56":"BUNALTMAK","13":"SOLİPSİZM","57":"KABARMA","14":"İSTİHDAM","58":"LÜKSLÜK","15":"BAŞLANGIÇTA","59":"SÜRREALİST","16":"BAKINMAK","17":"ARINABİLME","18":"KİMYAGERLİK","19":"MERDİVENİMSİ","20":"VARTADAN","21":"SAKSAFONCU","22":"JEOPOLİTİK","23":"TEPELİKLİ","24":"SEFERBERLİK","25":"HÜZÜNLENMEK","26":"KAPSAMLILIK","27":"ACEMİCE","28":"TERTİPLENME","29":"BECEREBİLMEK","30":"ŞAMDANLIK","31":"BAKIMCI","32":"GÖZETME","33":"ANTENLİ","34":"DİLBAZLIK","35":"BARKODSUZ","36":"DARALIŞ","37":"ERENLER","38":"KÜFRETME","39":"SEFİRLİK","40":"ÇİMENTOSUZ","41":"ZARFSIZ","42":"BÜTÜNLEME","43":"UTANGAN"}