{"00":"İÇKİNLİK","44":"HİSTERİ","01":"SOBALIK","45":"PEKİŞTİRME","02":"İŞKEMBEDEN","46":"DOĞRULABİLME","03":"İŞARETLEYİŞ","47":"PLEYBEK","04":"İLKBAHAR","48":"YANSIMAK","05":"KITALAR","49":"MARULCU","06":"BEŞLEME","07":"DİŞLENME","08":"İHTİLAL","09":"ADIMLARINI","50":"EKMEĞİNE","51":"SAKSONYA","52":"PELTELEŞME","53":"YAKALAMA","10":"KERTİKLİ","54":"GÖKDELEN","11":"MANİPLE","55":"ÇEVRİLME","12":"BOBİNAJ","56":"EKMEKLE","13":"EFSANESİZ","57":"MARİFETLİ","14":"TUTABİLMEK","58":"DİDİKLEMEK","15":"GERİLEYİŞ","59":"HATMETME","16":"DALAŞMA","17":"TEKRARLAMAK","18":"ÜMİTSİZ","19":"İSTENMEYEN","20":"BALİNALAR","21":"TETKİKAT","22":"URANYUM","23":"TASFİYECİ","24":"YAKICILIK","25":"ÖLDÜRÜLME","26":"SİDİKLİ","27":"OKUYABİLME","28":"BORSACILIK","29":"CEVAHİR","30":"PERİYODİK","31":"ÇEŞNİCİ","32":"KUZULUK","33":"LİMONATACI","34":"BAŞÇAVUŞ","35":"KAYMAKAM","36":"MÜNTEŞİR","37":"ARTIRIM","38":"DUVAKLI","39":"REŞİTLİK","40":"YÜZYILLARCA","41":"MUAZZEP","42":"BAĞIMLI","43":"BEĞENİLMEK"}