{"00":"SERVİSÇİLİK","44":"BÜKÜLÜŞ","01":"KİMYASAL","45":"OLMAMIŞ","02":"HESAPSIZCA","46":"KOZAKLI","03":"KESMELİK","47":"BİNDİRMEK","04":"DÖNÜŞÜMLÜ","48":"DAYANAKLI","05":"ÇİMENTOLAMAK","49":"DERTLENMEK","06":"KEYFİNDEN","07":"BABACIL","08":"ETİKETLENME","09":"İTİBARIN","50":"KORDONE","51":"KIYILIK","52":"ANTRENÖR","53":"ÇALIŞIP","10":"ELEŞTİRMEN","54":"KURŞUNCULUK","11":"YETMİŞER","55":"ANTİLOPLAR","12":"HEREKLEME","56":"KLEPTOMANİ","13":"KAVMİYET","57":"KIRILIŞ","14":"RAPTETMEK","58":"ABDALIN","15":"BİTEVİYE","59":"EHLİYET","16":"BOŞBOĞAZ","17":"KÖKENSİZ","18":"ISLAHATÇI","19":"UZUNÇALAR","20":"İSTİARE","21":"YILANYASTIĞI","22":"BAĞDAŞIKLIK","23":"AFALLATMA","24":"SEMERCİ","25":"İZLENİMCİ","26":"AZDIRILMAK","27":"MÜMTENİ","28":"PAYLAŞMA","29":"SOLLAMAK","30":"MATERYALİST","31":"YILGINLIK","32":"TIRMALAMA","33":"İŞGÜDER","34":"KURALLI","35":"TEKERLEME","36":"ÇAĞLAYAN","37":"MUMYALANMAK","38":"HÜKÜMSÜZLÜK","39":"MEVZİLENİŞ","40":"ARSENİK","41":"ASABİYET","42":"TASAVVUFİ","43":"GİTMELİ"}