{"00":"BERKELYUM","44":"EKMEKÇİLİK","01":"SÜSLEME","45":"ZENGİNLEŞMEK","02":"MELUNLUK","46":"HUKUKÇULUK","03":"ÖPTÜRMEK","47":"KOMİSYONCU","04":"YUTTURMAK","48":"GÖZÜKME","05":"KATEGORİ","49":"TABANLI","06":"LEKELENME","07":"DİYECEK","08":"MANYETİZE","09":"VİDEOKASET","50":"CEHALET","51":"DEĞİŞTİRMEK","52":"SÖVDÜRMEK","53":"BEŞİNCİ","10":"MUAŞAKA","54":"ASILLIK","11":"MÜZİKÇİ","55":"ALÇAKLIK","12":"YIĞIŞMAK","56":"KISALTMALI","13":"TUTUŞTURMA","57":"KONUŞMAK","14":"ŞATAFATLI","58":"YAPIŞTIRILMA","15":"KALEMİYLE","59":"FRİJİDİTE","16":"AJİTASYON","17":"İLANİHAYE","18":"SÜRATLİLİK","19":"SOFİSTİKE","20":"LİYAKATSİZ","21":"İKAMETE","22":"ÖRÜCÜLÜK","23":"ÇÜRÜKSÜZ","24":"HALKALANMA","25":"KESİŞTİRMEK","26":"TAVŞANMEMESİ","27":"ORKİNOS","28":"ÇAĞANOZ","29":"SAKALIK","30":"İTHALAT","31":"FAVORİLİ","32":"DÜŞÜNÜŞ","33":"YAPTIRILMAK","34":"ORTANIN","35":"HİSSİNİ","36":"TÜKETEBİLME","37":"TIRMALAYIŞ","38":"AYBAŞILI","39":"ÇÖZÜLÜVERMEK","40":"MÜVESVİS","41":"POLİANDRİ","42":"BULANIK","43":"BÜYÜSÜZ"}