{"00":"ROBOTİK","44":"BİNDİRME","01":"AGNOSTİK","45":"AFFEDİŞ","02":"PERDELEYİCİ","46":"YERLEŞİKLİK","03":"ZURNADA","47":"AYKIRILIK","04":"İTİRAZCILIK","48":"MEMLEKET","05":"TÖKEZLEMEK","49":"BAHARİYE","06":"NOKTALANMA","07":"GARDENYA","08":"SALİSELİK","09":"KENDİNE","50":"UMURSAMAZLIK","51":"KIRPIŞTIRMA","52":"ÜSTELEME","53":"KULÜPÇÜ","10":"AMELİYATLI","54":"KOLAYLAMA","11":"TOPLANAN","55":"DİLAVER","12":"RUTİNLİK","56":"REPERTUVAR","13":"YİRMİŞER","57":"ASTİGMATİZM","14":"GÜNLÜKÇÜ","58":"SÖYLEŞİCİ","15":"BAHARİYE","59":"HANIMGÖBEĞİ","16":"SULANDIRILMA","17":"ANAYASAL","18":"ARKADAŞÇA","19":"SARSINTILI","20":"KINDIRA","21":"ETEĞİYLE","22":"ÜRPERİŞ","23":"LİKORİNOZ","24":"SERVİSE","25":"BATILILAŞMAK","26":"TAKIŞMA","27":"AHİRETLİK","28":"EVCİLİK","29":"KONDÜKTÖR","30":"BAŞKALAŞMA","31":"MALİYETSİZ","32":"İLTİHAPLANMA","33":"SAKARİN","34":"GERÇEKLEME","35":"EMZİKSİZ","36":"KUCAKLAMA","37":"DÜRBÜNLÜ","38":"YELPAZE","39":"HASSATEN","40":"DİLEMEK","41":"GADDARCA","42":"MATLAŞMAK","43":"SUÇLANMA"}